pycake/__init__.py
pycake/api/AdminAPI.py
pycake/api/AffiliateAPI.py
pycake/api/BuyerAPI.py
pycake/api/ResponseFormat.py
pycake/api/__init__.py
pycake/api/function_validation.py
pycake/models/BrandAdvertiser.py
pycake/models/CakeModel.py
pycake/models/Campaign.py
pycake/models/Click.py
pycake/models/EventConversion.py
pycake/models/SiteOffer.py
pycake/models/SourceAffiliate.py
pycake/models/__init__.py
pycake-2.1.0.data/data/LICENSE.txt
pycake-2.1.0.dist-info/DESCRIPTION.rst
pycake-2.1.0.dist-info/METADATA
pycake-2.1.0.dist-info/RECORD
pycake-2.1.0.dist-info/WHEEL
pycake-2.1.0.dist-info/metadata.json
pycake-2.1.0.dist-info/top_level.txt
