Metadata-Version: 2.0
Name: pycake
Version: 2.1.0
Summary: Python SDK for CAKE API
Home-page: https://github.com/heytimj/pycake
Author: Timothy Johnson
Author-email: tim@getcake.com
License: MIT
Download-URL: https://github.com/heytimj/pycake/archive/2.1.0.tar.gz
Keywords: cake,api,sdk
Platform: UNKNOWN
Requires-Dist: requests
